interactive_time_tracker.py
interactive_time_tracker-0.1.0.dist-info/LICENSE
interactive_time_tracker-0.1.0.dist-info/WHEEL
interactive_time_tracker-0.1.0.dist-info/METADATA
interactive_time_tracker-0.1.0.dist-info/RECORD
