Metadata-Version: 2.1
Name: interactive-time-tracker
Version: 0.1.0
Summary: A tool to measure elapsed time of functions
License: MIT
Author: Jéssica Meneguel
Requires-Python: >=3.9,<4.0
Classifier: License :: OSI Approved :: MIT License
Classifier: Programming Language :: Python :: 3
Classifier: Programming Language :: Python :: 3.10
Classifier: Programming Language :: Python :: 3.9
